ProjectAssessment/MakeTable.py
ProjectAssessment/Marginal.py
ProjectAssessment/Solver.py
ProjectAssessment/__init__.py
projectassessment-0.3.8.dist-info/METADATA
projectassessment-0.3.8.dist-info/WHEEL
projectassessment-0.3.8.dist-info/licenses/LICENSE
projectassessment-0.3.8.dist-info/RECORD
