Metadata-Version: 2.3
Name: ProjectAssessment
Version: 0.3.8
Summary: Package to compute the Project-Based Assessment estimates of student and rubric proficiency.
Project-URL: Homepage, https://github.com/tazzben/project-based-assessment
Project-URL: Bug Tracker, https://github.com/tazzben/project-based-assessment/issues
Author-email: Ben Smith <bosmith@unomaha.edu>
Maintainer-email: Ben Smith <bosmith@unomaha.edu>
License-Expression: MIT
License-File: LICENSE
Keywords: Assessment,Bootstrap,Education,Projects,Statistics
Classifier: Development Status :: 5 - Production/Stable
Classifier: Intended Audience :: Science/Research
Classifier: License :: OSI Approved :: MIT License
Classifier: Programming Language :: Python :: 3.9
Classifier: Programming Language :: Python :: 3.10
Classifier: Programming Language :: Python :: 3.11
Classifier: Programming Language :: Python :: 3.12
Requires-Python: >=3.9
Requires-Dist: numba>=0.54.0
Requires-Dist: numpy>=1.21.0
Requires-Dist: pandas>=1.3.0
Requires-Dist: scipy>=1.4.0
Requires-Dist: tqdm>=4.26.0
